<xml>
	<request name="Calendar" version="GCal 11">
		<arg name="longitude" val="+30.52340" />
		<arg name="latitude" val="+50.45010" />
		<arg name="timezone" val="+2.00000" />
		<arg name="startdate" val="1 Jul 2021" />
		<arg name="daycount" val="31" />
		<arg name="dst" val="x810590288" />
	</request>
	<result name="Calendar">
	<masa name="Vamana Masa" gyear="Gaurabda 535">
	<day date="1 Jul 2021" dayweekid="4" dayweek="Th">
		<sunrise time="04:50:39">
			<tithi name="Saptami" elapse="73.1" index="7"/>
			<naksatra name="Uttara-bhadra" elapse="20.7" />
			<yoga name="Saubhagya" />
			<paksa id="K" name="Krsna"/>
		</sunrise>
		<dst offset="1" />
		<arunodaya time="03:14:39">
			<tithi name="Saptami" />
		</arunodaya>
		<noon time="13:01:39" />
		<sunset time="21:12:39" />
		<moon rise="00:52:53" set="12:24:20" />
		<vriddhi sd="no" />
	</day>

	<day date="2 Jul 2021" dayweekid="5" dayweek="Fr">
		<sunrise time="04:51:20">
			<tithi name="Astami" elapse="68.2" index="8"/>
			<naksatra name="Revati" elapse="13.4" />
			<yoga name="Sobana" />
			<paksa id="K" name="Krsna"/>
		</sunrise>
		<dst offset="1" />
		<arunodaya time="03:15:20">
			<tithi name="Astami" />
		</arunodaya>
		<noon time="13:01:50" />
		<sunset time="21:12:20" />
		<moon rise="01:07:50" set="13:33:25" />
		<vriddhi sd="no" />
	</day>

	<day date="3 Jul 2021" dayweekid="6" dayweek="Sa">
		<sunrise time="04:52:03">
			<tithi name="Navami" elapse="61.1" index="9"/>
			<naksatra name="Asvini" elapse="4.2" />
			<yoga name="Atiganda" />
			<paksa id="K" name="Krsna"/>
		</sunrise>
		<dst offset="1" />
		<arunodaya time="03:16:03">
			<tithi name="Navami" />
		</arunodaya>
		<noon time="13:02:00" />
		<sunset time="21:11:57" />
		<moon rise="01:22:30" set="14:41:16" />
		<vriddhi sd="no" />
	</day>

	<day date="4 Jul 2021" dayweekid="0" dayweek="Su">
		<sunrise time="04:52:49">
			<tithi name="Dasami" elapse="52.5" index="10"/>
			<naksatra name="Asvini" elapse="93.6" />
			<yoga name="Sukarma" />
			<paksa id="K" name="Krsna"/>
		</sunrise>
		<dst offset="1" />
		<arunodaya time="03:16:49">
			<tithi name="Dasami" />
		</arunodaya>
		<noon time="13:02:10" />
		<sunset time="21:11:31" />
		<moon rise="01:37:58" set="15:48:54" />
		<festival name="Sri Srivasa Pandita -- Disappearance" class="3"/>
		<vriddhi sd="no" />
	</day>

	<day date="5 Jul 2021" dayweekid="1" dayweek="Mo">
		<sunrise time="04:53:36">
			<tithi name="Ekadasi (suitable for fasting)" elapse="43.0" index="11"/>
			<naksatra name="Bharani" elapse="82.2" />
			<yoga name="Dhriti" />
			<paksa id="K" name="Krsna"/>
		</sunrise>
		<dst offset="1" />
		<arunodaya time="03:17:36">
			<tithi name="Ekadasi" />
		</arunodaya>
		<noon time="13:02:19" />
		<sunset time="21:11:03" />
		<moon rise="01:55:25" set="16:56:45" />
		<festival name="Fasting for Yogini Ekadasi" class="-1"/>
		<fast type="" mark="*" />
		<vriddhi sd="no" />
	</day>

	<day date="6 Jul 2021" dayweekid="2" dayweek="Tu">
		<sunrise time="04:54:26">
			<tithi name="Dvadasi" elapse="33.3" index="12"/>
			<naksatra name="Krittika" elapse="70.7" />
			<yoga name="Sula" />
			<paksa id="K" name="Krsna"/>
		</sunrise>
		<dst offset="1" />
		<arunodaya time="03:18:26">
			<tithi name="Dvadasi" />
		</arunodaya>
		<noon time="13:02:29" />
		<sunset time="21:10:31" />
		<moon rise="02:16:16" set="18:04:24" />
		<parana from="04:54" to="10:19" />
		<vriddhi sd="no" />
	</day>

	<day date="7 Jul 2021" dayweekid="3" dayweek="We">
		<sunrise time="04:55:19">
			<tithi name="Trayodasi" elapse="24.0" index="13"/>
			<naksatra name="Rohini" elapse="59.4" />
			<yoga name="Ganda" />
			<paksa id="K" name="Krsna"/>
		</sunrise>
		<dst offset="1" />
		<arunodaya time="03:19:19">
			<tithi name="Trayodasi" />
		</arunodaya>
		<noon time="13:02:38" />
		<sunset time="21:09:57" />
		<moon rise="02:42:19" set="19:10:15" />
		<vriddhi sd="no" />
	</day>

	<day date="8 Jul 2021" dayweekid="4" dayweek="Th">
		<sunrise time="04:56:13">
			<tithi name="Caturdasi" elapse="15.5" index="14"/>
			<naksatra name="Mrigasira" elapse="49.0" />
			<yoga name="Vriddhi" />
			<paksa id="K" name="Krsna"/>
		</sunrise>
		<dst offset="1" />
		<arunodaya time="03:20:13">
			<tithi name="Caturdasi" />
		</arunodaya>
		<noon time="13:02:46" />
		<sunset time="21:09:19" />
		<moon rise="03:15:45" set="20:11:32" />
		<vriddhi sd="no" />
	</day>

	<day date="9 Jul 2021" dayweekid="5" dayweek="Fr">
		<sunrise time="04:57:09">
			<tithi name="Amavasya" elapse="8.3" index="15"/>
			<naksatra name="Ardra" elapse="39.6" />
			<yoga name="Dhruva" />
			<paksa id="K" name="Krsna"/>
		</sunrise>
		<dst offset="1" />
		<arunodaya time="03:21:09">
			<tithi name="Amavasya" />
		</arunodaya>
		<noon time="13:02:54" />
		<sunset time="21:08:39" />
		<moon rise="03:58:44" set="21:05:16" />
		<festival name="Sri Gadadhara Pandita -- Disappearance" class="3"/>
		<festival name="Srila Bhaktivinoda Thakura -- Disappearance" class="2"/>
		<festival name="(Fast till noon)" class="-1"/>
		<fast type="" mark="*" />
		<vriddhi sd="no" />
	</day>

	<day date="10 Jul 2021" dayweekid="6" dayweek="Sa">
		<sunrise time="04:58:07">
			<tithi name="Pratipat" elapse="2.6" index="16"/>
			<naksatra name="Punarvasu" elapse="31.7" />
			<yoga name="Vyagata" />
			<paksa id="G" name="Gaura"/>
		</sunrise>
		<dst offset="1" />
		<arunodaya time="03:22:07">
			<tithi name="Amavasya" />
		</arunodaya>
		<noon time="13:03:02" />
		<sunset time="21:07:57" />
		<moon rise="04:52:26" set="21:49:41" />
		<vriddhi sd="no" />
	</day>

	<day date="11 Jul 2021" dayweekid="0" dayweek="Su">
		<sunrise time="04:59:08">
			<tithi name="Pratipat" elapse="98.6" index="16"/>
			<naksatra name="Pusyami" elapse="25.2" />
			<yoga name="Harsana" />
			<paksa id="G" name="Gaura"/>
		</sunrise>
		<dst offset="1" />
		<arunodaya time="03:23:08">
			<tithi name="Pratipat" />
		</arunodaya>
		<noon time="13:03:09" />
		<sunset time="21:07:11" />
		<moon rise="05:55:59" set="22:25:01" />
		<festival name="Gundica Marjana" class="1"/>
		<vriddhi sd="yes" />
	</day>

	<day date="12 Jul 2021" dayweekid="1" dayweek="Mo">
		<sunrise time="05:00:10">
			<tithi name="Dvitiya" elapse="96.5" index="17"/>
			<naksatra name="Aslesa" elapse="20.4" />
			<yoga name="Vajra" />
			<paksa id="G" name="Gaura"/>
		</sunrise>
		<dst offset="1" />
		<arunodaya time="03:24:10">
			<tithi name="Dvitiya" />
		</arunodaya>
		<noon time="13:03:16" />
		<sunset time="21:06:23" />
		<moon rise="07:06:36" set="22:52:57" />
		<festival name="Ratha Yatra" class="1"/>
		<festival name="Sri Svarupa Damodara Gosvami -- Disappearance" class="3"/>
		<festival name="Sri Sivananda Sena -- Disappearance" class="3"/>
		<vriddhi sd="no" />
	</day>

	<day date="13 Jul 2021" dayweekid="2" dayweek="Tu">
		<sunrise time="05:01:13">
			<tithi name="Tritiya" elapse="96.1" index="18"/>
			<naksatra name="Magha" elapse="17.3" />
			<yoga name="Siddhi" />
			<paksa id="G" name="Gaura"/>
		</sunrise>
		<dst offset="1" />
		<arunodaya time="03:25:13">
			<tithi name="Tritiya" />
		</arunodaya>
		<noon time="13:03:23" />
		<sunset time="21:05:32" />
		<moon rise="08:21:05" set="23:15:35" />
		<vriddhi sd="no" />
	</day>

	<day date="14 Jul 2021" dayweekid="3" dayweek="We">
		<sunrise time="05:02:19">
			<tithi name="Caturthi" elapse="97.7" index="19"/>
			<naksatra name="Purva-phalguni" elapse="15.9" />
			<yoga name="Vyatipata" />
			<paksa id="G" name="Gaura"/>
		</sunrise>
		<dst offset="1" />
		<arunodaya time="03:26:19">
			<tithi name="Caturthi" />
		</arunodaya>
		<noon time="13:03:29" />
		<sunset time="21:04:38" />
		<moon rise="09:37:07" set="N/A" />
		<vriddhi sd="no" />
	</day>

	<day date="15 Jul 2021" dayweekid="4" dayweek="Th">
		<sunrise time="05:03:26">
			<tithi name="Sasti" elapse="1.1" index="21"/>
			<naksatra name="Uttara-phalguni" elapse="16.1" />
			<yoga name="Variyana" />
			<paksa id="G" name="Gaura"/>
		</sunrise>
		<dst offset="1" />
		<arunodaya time="03:27:26">
			<tithi name="Pancami" />
		</arunodaya>
		<noon time="13:03:34" />
		<sunset time="21:03:42" />
		<moon rise="10:53:52" set="N/A" />
		<festival name="Sri Vakresvara Pandita -- Disappearance" class="3"/>
		<ksaya from="05:34" to="04:48" />
		<vriddhi sd="no" />
	</day>

	<day date="16 Jul 2021" dayweekid="5" dayweek="Fr">
		<sunrise time="05:04:35">
			<tithi name="Saptami" elapse="6.3" index="22"/>
			<naksatra name="Hasta" elapse="18.0" />
			<yoga name="Parigha" />
			<paksa id="G" name="Gaura"/>
		</sunrise>
		<dst offset="1" />
		<arunodaya time="03:28:35">
			<tithi name="Sasti" />
		</arunodaya>
		<noon time="13:03:39" />
		<sunset time="21:02:44" />
		<moon rise="12:11:33" set="N/A" />
		<festival name="Hera Pancami (4 days after Ratha Yatra)" class="1"/>
		<vriddhi sd="no" />
	</day>

	<day date="17 Jul 2021" dayweekid="6" dayweek="Sa">
		<sunrise time="05:05:45">
			<tithi name="Astami" elapse="13.4" index="23"/>
			<naksatra name="Citra" elapse="21.5" />
			<yoga name="Siddha" />
			<paksa id="G" name="Gaura"/>
		</sunrise>
		<dst offset="1" />
		<arunodaya time="03:29:45">
			<tithi name="Astami" />
		</arunodaya>
		<noon time="13:03:44" />
		<sunset time="21:01:42" />
		<moon rise="13:31:03" set="00:09:08" />
		<sankranti rasi="Karka" time="14:15:57" />
		<vriddhi sd="no" />
	</day>

	<day date="18 Jul 2021" dayweekid="0" dayweek="Su">
		<sunrise time="05:06:57">
			<tithi name="Navami" elapse="22.3" index="24"/>
			<naksatra name="Swati" elapse="26.7" />
			<yoga name="Sadhya" />
			<paksa id="G" name="Gaura"/>
		</sunrise>
		<dst offset="1" />
		<arunodaya time="03:30:57">
			<tithi name="Navami" />
		</arunodaya>
		<noon time="13:03:48" />
		<sunset time="21:00:39" />
		<moon rise="14:53:13" set="00:27:06" />
		<vriddhi sd="no" />
	</day>

	<day date="19 Jul 2021" dayweekid="1" dayweek="Mo">
		<sunrise time="05:08:10">
			<tithi name="Dasami" elapse="32.9" index="25"/>
			<naksatra name="Visakha" elapse="33.4" />
			<yoga name="Subha" />
			<paksa id="G" name="Gaura"/>
		</sunrise>
		<dst offset="1" />
		<arunodaya time="03:32:10">
			<tithi name="Dasami" />
		</arunodaya>
		<noon time="13:03:51" />
		<sunset time="20:59:32" />
		<moon rise="16:18:05" set="00:47:48" />
		<vriddhi sd="no" />
	</day>

	<day date="20 Jul 2021" dayweekid="2" dayweek="Tu">
		<sunrise time="05:09:25">
			<tithi name="Ekadasi (suitable for fasting)" elapse="45.1" index="26"/>
			<naksatra name="Anuradha" elapse="41.5" />
			<yoga name="Sukla" />
			<paksa id="G" name="Gaura"/>
		</sunrise>
		<dst offset="1" />
		<arunodaya time="03:33:25">
			<tithi name="Ekadasi" />
		</arunodaya>
		<noon time="13:03:54" />
		<sunset time="20:58:24" />
		<moon rise="17:43:36" set="01:13:37" />
		<festival name="Fasting for Sayana Ekadasi" class="-1"/>
		<festival name="Return Ratha (8 days after Ratha Yatra)" class="1"/>
		<fast type="" mark="*" />
		<vriddhi sd="no" />
	<caturmasya day="first" month="1" system="EKADASI" />
	</day>

	<day date="21 Jul 2021" dayweekid="3" dayweek="We">
		<sunrise time="05:10:40">
			<tithi name="Dvadasi" elapse="58.3" index="27"/>
			<naksatra name="Jyestha" elapse="50.6" />
			<yoga name="Brahma" />
			<paksa id="G" name="Gaura"/>
		</sunrise>
		<dst offset="1" />
		<arunodaya time="03:34:40">
			<tithi name="Dvadasi" />
		</arunodaya>
		<noon time="13:03:57" />
		<sunset time="20:57:13" />
		<moon rise="19:04:39" set="01:47:51" />
		<parana from="05:10" to="10:26" />
		<vriddhi sd="no" />
	</day>

	<day date="22 Jul 2021" dayweekid="4" dayweek="Th">
		<sunrise time="05:11:57">
			<tithi name="Trayodasi" elapse="72.1" index="28"/>
			<naksatra name="Mula" elapse="60.1" />
			<yoga name="Indra" />
			<paksa id="G" name="Gaura"/>
		</sunrise>
		<dst offset="1" />
		<arunodaya time="03:35:57">
			<tithi name="Trayodasi" />
		</arunodaya>
		<noon time="13:03:59" />
		<sunset time="20:56:00" />
		<moon rise="20:14:21" set="02:34:29" />
		<vriddhi sd="no" />
	</day>

	<day date="23 Jul 2021" dayweekid="5" dayweek="Fr">
		<sunrise time="05:13:15">
			<tithi name="Caturdasi" elapse="85.7" index="29"/>
			<naksatra name="Purva-asadha" elapse="69.5" />
			<yoga name="Vaidhriti" />
			<paksa id="G" name="Gaura"/>
		</sunrise>
		<dst offset="1" />
		<arunodaya time="03:37:15">
			<tithi name="Caturdasi" />
		</arunodaya>
		<noon time="13:04:00" />
		<sunset time="20:54:44" />
		<moon rise="21:08:29" set="03:36:05" />
		<vriddhi sd="no" />
	</day>

	<day date="24 Jul 2021" dayweekid="6" dayweek="Sa">
		<sunrise time="05:14:34">
			<tithi name="Purnima" elapse="98.1" index="30"/>
			<naksatra name="Uttara-asadha" elapse="77.9" />
			<yoga name="Priti" />
			<paksa id="G" name="Gaura"/>
		</sunrise>
		<dst offset="1" />
		<arunodaya time="03:38:34">
			<tithi name="Purnima" />
		</arunodaya>
		<noon time="13:04:01" />
		<sunset time="20:53:27" />
		<moon rise="21:48:03" set="04:50:35" />
		<festival name="Guru (Vyasa) Purnima" class="1"/>
		<festival name="Srila Sanatana Gosvami -- Disappearance" class="3"/>
		<vriddhi sd="no" />
		<caturmasya day="first" month="1" system="PURNIMA" />
	</day>

	</masa>
	<masa name="Sridhara Masa" gyear="Gaurabda 535">
	<day date="25 Jul 2021" dayweekid="0" dayweek="Su">
		<sunrise time="05:15:54">
			<tithi name="Dvitiya" elapse="8.6" index="2"/>
			<naksatra name="Sravana" elapse="84.5" />
			<yoga name="Ayusmana" />
			<paksa id="K" name="Krsna"/>
		</sunrise>
		<dst offset="1" />
		<arunodaya time="03:39:54">
			<tithi name="Dvitiya" />
		</arunodaya>
		<noon time="13:04:01" />
		<sunset time="20:52:07" />
		<moon rise="22:16:58" set="06:11:40" />
		<ksaya from="05:38" to="03:22" />
		<vriddhi sd="no" />
		<caturmasya day="first" month="1" system="PRATIPAT" />
	</day>

	<day date="26 Jul 2021" dayweekid="1" dayweek="Mo">
		<sunrise time="05:17:16">
			<tithi name="Tritiya" elapse="16.3" index="3"/>
			<naksatra name="Dhanista" elapse="88.6" />
			<yoga name="Saubhagya" />
			<paksa id="K" name="Krsna"/>
		</sunrise>
		<dst offset="1" />
		<arunodaya time="03:41:16">
			<tithi name="Tritiya" />
		</arunodaya>
		<noon time="13:04:00" />
		<sunset time="20:50:45" />
		<moon rise="22:39:02" set="07:33:04" />
		<vriddhi sd="no" />
	</day>

	<day date="27 Jul 2021" dayweekid="2" dayweek="Tu">
		<sunrise time="05:18:38">
			<tithi name="Caturthi" elapse="20.9" index="4"/>
			<naksatra name="Satabhisa" elapse="89.9" />
			<yoga name="Sobana" />
			<paksa id="K" name="Krsna"/>
		</sunrise>
		<dst offset="1" />
		<arunodaya time="03:42:38">
			<tithi name="Caturthi" />
		</arunodaya>
		<noon time="13:03:59" />
		<sunset time="20:49:21" />
		<moon rise="22:56:59" set="08:51:29" />
		<vriddhi sd="no" />
	</day>

	<day date="28 Jul 2021" dayweekid="3" dayweek="We">
		<sunrise time="05:20:00">
			<tithi name="Pancami" elapse="22.1" index="5"/>
			<naksatra name="Purva-bhadra" elapse="88.2" />
			<yoga name="Atiganda" />
			<paksa id="K" name="Krsna"/>
		</sunrise>
		<dst offset="1" />
		<arunodaya time="03:44:00">
			<tithi name="Pancami" />
		</arunodaya>
		<noon time="13:03:58" />
		<sunset time="20:47:55" />
		<moon rise="23:12:44" set="10:06:07" />
		<festival name="Srila Gopala Bhatta Gosvami -- Disappearance" class="3"/>
		<vriddhi sd="no" />
	</day>

	<day date="29 Jul 2021" dayweekid="4" dayweek="Th">
		<sunrise time="05:21:24">
			<tithi name="Sasti" elapse="20.2" index="6"/>
			<naksatra name="Uttara-bhadra" elapse="83.6" />
			<yoga name="Sukarma" />
			<paksa id="K" name="Krsna"/>
		</sunrise>
		<dst offset="1" />
		<arunodaya time="03:45:24">
			<tithi name="Sasti" />
		</arunodaya>
		<noon time="13:03:56" />
		<sunset time="20:46:28" />
		<moon rise="N/A" set="11:17:36" />
		<vriddhi sd="no" />
	</day>

	<day date="30 Jul 2021" dayweekid="5" dayweek="Fr">
		<sunrise time="05:22:48">
			<tithi name="Saptami" elapse="15.4" index="7"/>
			<naksatra name="Revati" elapse="76.5" />
			<yoga name="Dhriti" />
			<paksa id="K" name="Krsna"/>
		</sunrise>
		<dst offset="1" />
		<arunodaya time="03:46:48">
			<tithi name="Saptami" />
		</arunodaya>
		<noon time="13:03:53" />
		<sunset time="20:44:58" />
		<moon rise="N/A" set="12:27:03" />
		<vriddhi sd="no" />
	</day>

	<day date="31 Jul 2021" dayweekid="6" dayweek="Sa">
		<sunrise time="05:24:14">
			<tithi name="Astami" elapse="8.4" index="8"/>
			<naksatra name="Asvini" elapse="67.3" />
			<yoga name="Sula" />
			<paksa id="K" name="Krsna"/>
		</sunrise>
		<dst offset="1" />
		<arunodaya time="03:48:14">
			<tithi name="Astami" />
		</arunodaya>
		<noon time="13:03:50" />
		<sunset time="20:43:26" />
		<moon rise="N/A" set="13:35:33" />
		<festival name="Srila Lokanatha Gosvami -- Disappearance" class="3"/>
		<vriddhi sd="no" />
	</day>

	</masa>
</result>
</xml>
